{
  "meta": {
    "stableOrder": true
  },
  "lockfileVersion": 3,
  "ATTENTION": "THIS IS AN AUTOGENERATED FILE. DO NOT EDIT THIS FILE DIRECTLY.",
  "specifiers": {
    "@abner/refresh@^1.1.7": "@abner/refresh@1.1.7",
    "@learn/YWRandomUtils@../modules/common_har": "@learn/YWRandomUtils@../modules/common_har",
    "@learn/base_har@../modules/base_har": "@learn/base_har@../modules/base_har",
    "@learn/common_har@../modules/common_har": "@learn/common_har@../modules/common_har",
    "@learn/main_har@../modules/main_har": "@learn/main_har@../modules/main_har",
    "@learn/request_har@../modules/request_har": "@learn/request_har@../modules/request_har",
    "@learn/tiger_har@../tiger_har": "@learn/tiger_har@../tiger_har",
    "STHarLib@libs/STHarLib.har": "STHarLib@libs/STHarLib.har",
    "ShareHarLibs@../ShareHarLib": "ShareHarLibs@../ShareHarLib"
  },
  "packages": {
    "@abner/refresh@1.1.7": {
      "name": "@abner/refresh",
      "integrity": "sha512-SAqW/St4fnoWLoKyYcLVBYpiS4tXKjCEH82av3o6B2G0f1h1He8dML1N3jXVM7OsygE1C/yHQnSIQGWEHS9V3w==",
      "resolved": "https://repo.harmonyos.com/ohpm/@abner/refresh/-/refresh-1.1.7.har",
      "registryType": "ohpm"
    },
    "@learn/YWRandomUtils@../modules/common_har": {
      "name": "common_har",
      "resolved": "../modules/common_har",
      "registryType": "local"
    },
    "@learn/base_har@../modules/base_har": {
      "name": "base_har",
      "resolved": "../modules/base_har",
      "registryType": "local",
      "dependencies": {
        "@learn/common_har": "file:../common_har"
      }
    },
    "@learn/common_har@../modules/common_har": {
      "name": "common_har",
      "resolved": "../modules/common_har",
      "registryType": "local"
    },
    "@learn/main_har@../modules/main_har": {
      "name": "main_har",
      "resolved": "../modules/main_har",
      "registryType": "local",
      "dependencies": {
        "@learn/common_har": "file:../common_har",
        "@learn/base_har": "file:../base_har",
        "@learn/tiger_har": "file:../../tiger_har"
      }
    },
    "@learn/request_har@../modules/request_har": {
      "name": "request_har",
      "resolved": "../modules/request_har",
      "registryType": "local",
      "dependencies": {
        "@learn/YWRandomUtils": "file:../../modules/common_har"
      }
    },
    "@learn/tiger_har@../tiger_har": {
      "name": "tiger_har",
      "resolved": "../tiger_har",
      "registryType": "local",
      "dependencies": {
        "@learn/common_har": "file:../modules/common_har"
      }
    },
    "STHarLib@libs/STHarLib.har": {
      "name": "stharlib",
      "resolved": "libs/STHarLib.har",
      "registryType": "local"
    },
    "ShareHarLibs@../ShareHarLib": {
      "name": "shareharlib",
      "resolved": "../ShareHarLib",
      "registryType": "local",
      "packageType": "InterfaceHar"
    }
  }
}